MANIFEST.in
README.rst
changelog.rst
setup.py
fabric_vms/__init__.py
fabric_vms/openvms.py
fabric_vms.egg-info/PKG-INFO
fabric_vms.egg-info/SOURCES.txt
fabric_vms.egg-info/dependency_links.txt
fabric_vms.egg-info/requires.txt
fabric_vms.egg-info/top_level.txt
fabric_vms/pml/__init__.py
fabric_vms/pml/pml.py