Metadata-Version: 1.1
Name: fabric-vms
Version: 0.2.4.1
Summary: An addon for managing OpenVMS hosts with fabric
Home-page: https://github.com/fernandezcuesta/fabric_vms
Author: JM Fernández
Author-email: fernandez.cuesta@gmail.com
License: MIT
Platform: all
Classifier: Development Status :: 4 - Beta
Classifier: Environment :: Console
Classifier: License :: OSI Approved :: GNU Affero General Public License v3
Classifier: Operating System :: OS Independent
Classifier: Programming Language :: Python :: 2 :: Only
Classifier: Topic :: System :: Systems Administration
